django_docdata-0.9.dist-info/DESCRIPTION.rst
django_docdata-0.9.dist-info/METADATA
django_docdata-0.9.dist-info/RECORD
django_docdata-0.9.dist-info/WHEEL
django_docdata-0.9.dist-info/metadata.json
django_docdata-0.9.dist-info/pbr.json
django_docdata-0.9.dist-info/top_level.txt
docdata/__init__.py
docdata/exceptions.py
docdata/interface.py
docdata/listeners.py
docdata/models.py
docdata/settings.py
docdata/signals.py
docdata/urls.py
docdata/views.py
tests/__init__.py
tests/base.py
tests/test_offline.py
tests/test_online.py
