Metadata-Version: 2.0
Name: django-docdata
Version: 0.9
Summary: Python/Django client to the Docdata payment system.
Home-page: http://github.com/dokterbob/django-docdata/
Author: Mathijs de Bruin
Author-email: mathijs@mathijsfietst.nl
License: AGPL
Platform: UNKNOWN
Classifier: Development Status :: 4 - Beta
Classifier: Intended Audience :: Developers
Classifier: Framework :: Django
Classifier: License :: OSI Approved :: GNU Affero General Public License v3
Classifier: Natural Language :: English
Classifier: Operating System :: OS Independent
Classifier: Programming Language :: Python
Classifier: Topic :: Software Development :: Libraries :: Python Modules
Classifier: Environment :: Web Environment
Requires-Dist: Django (>=1.8.13)
Requires-Dist: requests (>=2.9.1,<3.0)
